pituophis/__init__.py
Pituophis-1.1.dist-info/LICENSE
Pituophis-1.1.dist-info/METADATA
Pituophis-1.1.dist-info/WHEEL
Pituophis-1.1.dist-info/top_level.txt
Pituophis-1.1.dist-info/RECORD
