Metadata-Version: 2.1
Name: Pituophis
Version: 1.1
Summary: Python 3 library for building Gopher clients and servers
Home-page: https://github.com/dotcomboom/Pituophis
Author: dotcomboom
Author-email: dotcomboom@somnolescent.net
License: BSD 2-Clause License
Platform: UNKNOWN
Classifier: Development Status :: 5 - Production/Stable
Classifier: Intended Audience :: Developers
Classifier: Intended Audience :: Information Technology
Classifier: Natural Language :: English
Classifier: Programming Language :: Python :: 3
Classifier: License :: OSI Approved :: BSD License
Classifier: Operating System :: OS Independent
